flake8_pyspark_with_column.py
flake8_pyspark_with_column-0.0.6.dist-info/METADATA
flake8_pyspark_with_column-0.0.6.dist-info/WHEEL
flake8_pyspark_with_column-0.0.6.dist-info/entry_points.txt
flake8_pyspark_with_column-0.0.6.dist-info/licenses/LICENSE
flake8_pyspark_with_column-0.0.6.dist-info/RECORD
