Metadata-Version: 2.4
Name: flake8-pyspark-with-column
Version: 0.0.6
Summary: A Flake8 plugin to check for PySpark withColumn usage in loops
Project-URL: Homepage, https://github.com/SemyonSinchenko/flake8-pyspark-with-column
Project-URL: Repository, https://github.com/SemyonSinchenko/flake8-pyspark-with-column.git
Author-email: Sem Sinchenko <ssinchenko@apache.org>
License-Expression: Apache-2.0
License-File: LICENSE
Keywords: flake8,linter,pyspark,quality
Classifier: Environment :: Console
Classifier: Framework :: Flake8
Classifier: Intended Audience :: Developers
Classifier: License :: OSI Approved :: MIT License
Classifier: Programming Language :: Python
Classifier: Programming Language :: Python :: 3
Classifier: Programming Language :: Python :: 3.7
Classifier: Programming Language :: Python :: 3.8
Classifier: Programming Language :: Python :: 3.9
Classifier: Programming Language :: Python :: 3.10
Classifier: Topic :: Software Development :: Libraries :: Python Modules
Classifier: Topic :: Software Development :: Quality Assurance
Requires-Dist: flake8>=3.0.0
